{"scope.version":"2","timeline.animationMode":"proMode","viewport.width":728,"viewport.height":90,"library.openDirectories":[],"library.GroupsPath":{},"library.downloadedAssets":{},"publish.local.location":"/Users/paolo/Desktop/Adlib/Working/2020/11 Nov/Purina Gourmet_UK_20Q4_Display - Purina - Display/11.18.2020/published/","publish.local.name":"728x90-Purina Gourmet UK","publish.local.flatten":true,"publish.local.minify":true,"publish.local.inlineFiles":true,"publish.local.createZip":false,"publish.local.politeLoad":true,"publish.local.exportMozilla":true,"publish.local.exportWebkit":true,"publish.local.unpackGroups":true,"publish.local.borderColor":"rgba(45,45,45,1)","publish.local.addBorder":true,"design.zoom":1.5,"tool.text.optionsState":{"fontName":"Times","fontSize":"16px","fontWeight":"normal","fontStyle":"normal","alignLeft":true,"alignCenter":false,"alignRight":false,"alignJustify":false,"verticalAlignCenter":false,"foreColor":"rgb(0, 0, 0)","tagName":"span","orderedList":false,"unorderedList":false},"":false,"publish.local.skipLoadingDelay":true}